{
  "ok": true,
  "generatedAt": "2026-03-21T23:00:04.827Z",
  "tz": "Europe/London",
  "todayTz": "2026-03-21",
  "lookbackDays": 45,
  "currency": "GBP",
  "totals": {
    "today": {
      "orders": 1,
      "revenue": 50,
      "aov": 50
    },
    "last7d": {
      "orders": 3,
      "revenue": 394,
      "aov": 131.33
    },
    "last28d": {
      "orders": 14,
      "revenue": 1519,
      "aov": 108.5
    },
    "mtd": {
      "orders": 10,
      "revenue": 1199,
      "aov": 119.9
    }
  },
  "sample": {
    "fetchedOrders": 50,
    "newestCreatedOn": "2026-03-21T18:50:20.453Z",
    "oldestCreatedOn": "2025-01-02T18:18:27.655Z"
  }
}